vibravox/__init__.py
vibravox/utils.py
vibravox/datasets/__init__.py
vibravox/datasets/speech_noise.py
vibravox/lightning_datamodules/__init__.py
vibravox/lightning_datamodules/bwe.py
vibravox/lightning_datamodules/noisybwe.py
vibravox/lightning_datamodules/spkv.py
vibravox/lightning_datamodules/stp.py
vibravox/lightning_modules/__init__.py
vibravox/lightning_modules/eben.py
vibravox/lightning_modules/ecapa2.py
vibravox/lightning_modules/wav2vec2_for_stp.py
vibravox/metrics/__init__.py
vibravox/metrics/embedding_distance.py
vibravox/metrics/equal_error_rate.py
vibravox/metrics/minimum_dcf.py
vibravox/metrics/noresqa_mos.py
vibravox/metrics/torchsquim_stoi.py
vibravox/torch_modules/utils.py
vibravox/torch_modules/dnn/__init__.py
vibravox/torch_modules/dnn/eben_discriminator.py
vibravox/torch_modules/dnn/eben_generator.py
vibravox/torch_modules/dnn/melgan_discriminator.py
vibravox/torch_modules/dsp/__init__.py
vibravox/torch_modules/dsp/data_augmentation.py
vibravox/torch_modules/dsp/pqmf.py
vibravox/torch_modules/dsp/time_masking_waveform.py
vibravox/torch_modules/losses/__init__.py
vibravox/torch_modules/losses/feature_loss.py
vibravox/torch_modules/losses/hinge_loss.py
vibravox-0.1.1.dist-info/licenses/LICENSE
vibravox-0.1.1.dist-info/METADATA
vibravox-0.1.1.dist-info/WHEEL
vibravox-0.1.1.dist-info/top_level.txt
vibravox-0.1.1.dist-info/RECORD
