Metadata-Version: 2.4
Name: vibravox
Version: 0.1.1
Summary: Speech to Phoneme, Bandwidth Extension and Speaker Verification using the Vibravox dataset.
Author-email: Julien Hauret <j.hauret.33@gmail.com>
Requires-Python: ==3.12.0
License-File: LICENSE
Requires-Dist: moshi==0.2.4
Requires-Dist: isort
Requires-Dist: lightning
Requires-Dist: torchaudio
Requires-Dist: torchmetrics[audio]
Requires-Dist: hydra-core
Requires-Dist: rich
Requires-Dist: tensorboard
Requires-Dist: datasets[audio]
Requires-Dist: huggingface_hub[cli]
Requires-Dist: transformers
Requires-Dist: pytest
Requires-Dist: auraloss
Requires-Dist: levenshtein
Dynamic: license-file
